sql_helper/__init__.py
sql_helper/settings.ini
sql_helper/scripts/__init__.py
sql_helper/scripts/sql_ipython.py
tests/__init__.py
tests/test_mysql.py
tests/test_postgresql.py
tests/test_sqlite.py
sql_helper-0.1.0.dist-info/LICENSE.txt
sql_helper-0.1.0.dist-info/METADATA
sql_helper-0.1.0.dist-info/WHEEL
sql_helper-0.1.0.dist-info/entry_points.txt
sql_helper-0.1.0.dist-info/top_level.txt
sql_helper-0.1.0.dist-info/RECORD
