Metadata-Version: 2.1
Name: sql-helper
Version: 0.1.0
Summary: Helper funcs and tools for working with SQL in mysql, postgresql, and more
Home-page: https://github.com/kenjyco/sql-helper
Download-URL: https://github.com/kenjyco/sql-helper/tarball/v0.1.0
Author: Ken
Author-email: kenjyco@gmail.com
License: MIT
Keywords: sql,data,database,cli,command-line,sqlalchemy,mysql,postgresql,sqlite,helper,kenjyco
Platform: UNKNOWN
Classifier: Development Status :: 4 - Beta
Classifier: Environment :: Console
Classifier: Intended Audience :: Developers
Classifier: License :: OSI Approved :: MIT License
Classifier: Operating System :: MacOS :: MacOS X
Classifier: Operating System :: POSIX :: Linux
Classifier: Programming Language :: Python :: 3.6
Classifier: Programming Language :: Python :: 3.7
Classifier: Programming Language :: Python :: 3.8
Classifier: Programming Language :: Python :: 3.9
Classifier: Programming Language :: Python :: 3.10
Classifier: Programming Language :: Python :: 3.11
Classifier: Programming Language :: Python :: 3.12
Classifier: Programming Language :: Python :: 3.13
Classifier: Programming Language :: Python
Classifier: Programming Language :: SQL
Classifier: Topic :: Database
Classifier: Topic :: Software Development :: Libraries
Classifier: Topic :: Utilities
License-File: LICENSE.txt
Requires-Dist: bg-helper
Requires-Dist: click (>=6.0)
Requires-Dist: cryptography
Requires-Dist: psycopg2-binary (<3,>=2.8)
Requires-Dist: settings-helper
Requires-Dist: sqlalchemy (>=1.3)
Requires-Dist: sqlalchemy (!=2.0.0,!=2.0.1,!=2.0.10,!=2.0.11,!=2.0.12,!=2.0.13,!=2.0.14,!=2.0.15,!=2.0.16,!=2.0.17,!=2.0.18,!=2.0.19,!=2.0.2,!=2.0.20,!=2.0.21,!=2.0.22,!=2.0.23,!=2.0.24,!=2.0.25,!=2.0.26,!=2.0.27,!=2.0.28,!=2.0.29,!=2.0.3,!=2.0.30,!=2.0.4,!=2.0.5.post1,!=2.0.6,!=2.0.7,!=2.0.8,!=2.0.9,>=1.3) ; python_version == "3.13"
Requires-Dist: pymysql (>=0.9.3) ; python_version == "3.6"
Requires-Dist: pymysql (>=1.1.1) ; python_version >= "3.7"
